obsei/__init__.py
obsei/_version.py
obsei/configuration.py
obsei/payload.py
obsei/process_workflow.py
obsei/processor.py
obsei/analyzer/__init__.py
obsei/analyzer/base_analyzer.py
obsei/analyzer/classification_analyzer.py
obsei/analyzer/dummy_analyzer.py
obsei/analyzer/ner_analyzer.py
obsei/analyzer/pii_analyzer.py
obsei/analyzer/sentiment_analyzer.py
obsei/analyzer/translation_analyzer.py
obsei/misc/__init__.py
obsei/misc/gpu_util.py
obsei/misc/utils.py
obsei/misc/web_search.py
obsei/misc/youtube_reviews_scrapper.py
obsei/postprocessor/__init__.py
obsei/postprocessor/base_postprocessor.py
obsei/postprocessor/inference_aggregator.py
obsei/postprocessor/inference_aggregator_function.py
obsei/preprocessor/__init__.py
obsei/preprocessor/base_preprocessor.py
obsei/preprocessor/text_cleaner.py
obsei/preprocessor/text_cleaning_function.py
obsei/preprocessor/text_splitter.py
obsei/preprocessor/text_tokenizer.py
obsei/sink/__init__.py
obsei/sink/base_sink.py
obsei/sink/dailyget_sink.py
obsei/sink/elasticsearch_sink.py
obsei/sink/http_sink.py
obsei/sink/jira_sink.py
obsei/sink/logger_sink.py
obsei/sink/pandas_sink.py
obsei/sink/slack_sink.py
obsei/sink/zendesk_sink.py
obsei/source/__init__.py
obsei/source/appstore_scrapper.py
obsei/source/base_source.py
obsei/source/email_source.py
obsei/source/facebook_source.py
obsei/source/google_maps_reviews.py
obsei/source/google_news_source.py
obsei/source/pandas_source.py
obsei/source/playstore_reviews.py
obsei/source/playstore_scrapper.py
obsei/source/reddit_scrapper.py
obsei/source/reddit_source.py
obsei/source/twitter_source.py
obsei/source/website_crawler_source.py
obsei/source/youtube_reviews.py
obsei/source/youtube_scrapper.py
obsei/workflow/__init__.py
obsei/workflow/base_store.py
obsei/workflow/store.py
obsei/workflow/workflow.py
obsei-0.0.15.dist-info/METADATA
obsei-0.0.15.dist-info/WHEEL
obsei-0.0.15.dist-info/licenses/LICENSE
obsei-0.0.15.dist-info/RECORD
