Metadata-Version: 2.1
Name: obsei
Version: 0.0.15
Summary: Obsei is an automation tool for text analysis need
Project-URL: repository, https://github.com/obsei/obsei
Project-URL: homepage, https://obsei.com
Project-URL: documentation, https://obsei.com
Project-URL: changelog, https://github.com/obsei/obsei/releases
Author-email: Lalit Pagaria <lalit.pagaria@oraika.com>
Maintainer-email: Lalit Pagaria <lalit.pagaria@oraika.com>, Girish Patel <girish.patel@oraika.com>
License: Apache Version 2.0
License-File: LICENSE
Keywords: automation,cognitive-automation,customer-experience,customer-feedback,customer-feedback-analysis,customer-support,low-code,market-research,nlp,obsei,oraika,social-listening,workflow
Classifier: Development Status :: 2 - Pre-Alpha
Classifier: Intended Audience :: Customer Service
Classifier: Intended Audience :: Developers
Classifier: Intended Audience :: Information Technology
Classifier: Intended Audience :: Science/Research
Classifier: License :: OSI Approved :: Apache Software License
Classifier: Operating System :: OS Independent
Classifier: Programming Language :: Python :: 3
Classifier: Programming Language :: Python :: 3.8
Classifier: Programming Language :: Python :: 3.9
Classifier: Programming Language :: Python :: 3.10
Classifier: Programming Language :: Python :: 3.11
Classifier: Topic :: Scientific/Engineering :: Artificial Intelligence
Classifier: Topic :: Software Development :: Libraries :: Python Modules
Requires-Python: >=3.8
Requires-Dist: beautifulsoup4>=4.9.3
Requires-Dist: dateparser>=1.2.0
Requires-Dist: mmh3>=4.0.1
Requires-Dist: pydantic-settings>=2.1.0
Requires-Dist: pydantic>=2.5.3
Requires-Dist: python-dateutil>=2.8.2
Requires-Dist: pytz>=2023.3.post1
Requires-Dist: requests>=2.26.0
Requires-Dist: sqlalchemy>=2.0.24
Provides-Extra: all
Requires-Dist: obsei[analyzer,sink,source]; extra == 'all'
Provides-Extra: analyzer
Requires-Dist: nltk>=3.8.1; extra == 'analyzer'
Requires-Dist: presidio-analyzer>=2.2.351; extra == 'analyzer'
Requires-Dist: presidio-anonymizer>=2.2.351; extra == 'analyzer'
Requires-Dist: sentencepiece>=0.1.99; extra == 'analyzer'
Requires-Dist: spacy>=3.7.2; extra == 'analyzer'
Requires-Dist: torch>=2.1.2; extra == 'analyzer'
Requires-Dist: transformers>=4.36.2; extra == 'analyzer'
Requires-Dist: vadersentiment>=3.3.2; extra == 'analyzer'
Provides-Extra: app-store-scraper
Requires-Dist: app-store-reviews-reader>=1.2; extra == 'app-store-scraper'
Provides-Extra: atlassian-api
Requires-Dist: atlassian-python-api>=3.41.4; extra == 'atlassian-api'
Provides-Extra: dev
Requires-Dist: black>=22.10.0; extra == 'dev'
Requires-Dist: coverage>=6.5.0; extra == 'dev'
Requires-Dist: mypy>=0.991; extra == 'dev'
Requires-Dist: pip-tools>=6.10.0; extra == 'dev'
Requires-Dist: pre-commit>=2.20.0; extra == 'dev'
Requires-Dist: pytest>=7.2.0; extra == 'dev'
Requires-Dist: types-dateparser; extra == 'dev'
Requires-Dist: types-protobuf; extra == 'dev'
Requires-Dist: types-python-dateutil; extra == 'dev'
Requires-Dist: types-pytz; extra == 'dev'
Requires-Dist: types-pyyaml; extra == 'dev'
Requires-Dist: types-requests; extra == 'dev'
Provides-Extra: elasticsearch
Requires-Dist: elasticsearch>=8.11.1; extra == 'elasticsearch'
Provides-Extra: facebook-api
Requires-Dist: python-facebook-api>=0.15.0; extra == 'facebook-api'
Provides-Extra: google-news-scraper
Requires-Dist: googlenews>=1.6.12; extra == 'google-news-scraper'
Provides-Extra: google-play-api
Requires-Dist: google-api-python-client>=2.111.0; extra == 'google-play-api'
Provides-Extra: google-play-scraper
Requires-Dist: google-play-scraper>=1.2.4; extra == 'google-play-scraper'
Provides-Extra: gpl
Requires-Dist: trafilatura>=1.6.3; extra == 'gpl'
Provides-Extra: pandas
Requires-Dist: pandas>=2.0.3; extra == 'pandas'
Provides-Extra: reddit-api
Requires-Dist: praw>=7.7.1; extra == 'reddit-api'
Provides-Extra: reddit-scraper
Requires-Dist: reddit-rss-reader>=1.3.2; extra == 'reddit-scraper'
Provides-Extra: sink
Requires-Dist: obsei[atlassian-api,elasticsearch,pandas,slack-api]; extra == 'sink'
Provides-Extra: slack-api
Requires-Dist: slack-sdk>=3.26.1; extra == 'slack-api'
Provides-Extra: source
Requires-Dist: obsei[app-store-scraper,google-play-api,google-play-scraper,twitter-api]; extra == 'source'
Requires-Dist: obsei[facebook-api,google-news-scraper,pandas,reddit-api,reddit-scraper]; extra == 'source'
Provides-Extra: twitter-api
Requires-Dist: searchtweets-v2>=1.1.1; extra == 'twitter-api'
